superleaf/__init__.py
superleaf/collections/__init__.py
superleaf/collections/ordered_set.py
superleaf/collections/summable_dict.py
superleaf/dataframe/__init__.py
superleaf/dataframe/column_ops.py
superleaf/dataframe/comparison.py
superleaf/dataframe/display.py
superleaf/dataframe/selection.py
superleaf/dataframe/standardize.py
superleaf/dataframe/transform.py
superleaf/operators/__init__.py
superleaf/operators/base.py
superleaf/operators/comparison.py
superleaf/operators/getters.py
superleaf/operators/string.py
superleaf/operators/wrappers.py
superleaf/plotting/__init__.py
superleaf/plotting/intervals.py
superleaf/sequences/__init__.py
superleaf/sequences/serial.py
superleaf/stats/__init__.py
superleaf/stats/circular.py
superleaf/stats/count.py
superleaf/timeseries/__init__.py
superleaf/timeseries/datetime_utils.py
superleaf/timeseries/time_intervals.py
superleaf/utils/__init__.py
superleaf/utils/hashing.py
superleaf/utils/ipython.py
superleaf/utils/parallel.py
superleaf-0.2.4.dist-info/licenses/LICENSE
superleaf-0.2.4.dist-info/METADATA
superleaf-0.2.4.dist-info/WHEEL
superleaf-0.2.4.dist-info/top_level.txt
superleaf-0.2.4.dist-info/RECORD
