Metadata-Version: 2.4
Name: superleaf
Version: 0.2.4
Summary: A library for intuitive and readable data manipulation, using functional and pipeable syntax.
Author-email: Erik Schomburg <eschomburg@gmail.com>
Project-URL: Homepage, https://github.com/eschombu/superleaf
Project-URL: Issues, https://github.com/eschombu/superleaf/issues
Requires-Python: >=3.8
License-File: LICENSE
Requires-Dist: matplotlib
Requires-Dist: numpy
Requires-Dist: pandas
Requires-Dist: pendulum>=3.0.0
Requires-Dist: scipy
Provides-Extra: dev
Requires-Dist: flake8; extra == "dev"
Requires-Dist: pydata-sphinx-theme; extra == "dev"
Requires-Dist: pydoclint; extra == "dev"
Requires-Dist: pytest; extra == "dev"
Requires-Dist: pytest-mock; extra == "dev"
Provides-Extra: notebook
Requires-Dist: jupyter; extra == "notebook"
Provides-Extra: parallel
Requires-Dist: multiprocess; extra == "parallel"
Requires-Dist: pyarrow; extra == "parallel"
Requires-Dist: tqdm; extra == "parallel"
Dynamic: license-file
